t402/__init__.py
t402/chains.py
t402/cli.py
t402/common.py
t402/cosmos_paywall_template.py
t402/encoding.py
t402/evm_paywall_template.py
t402/exact.py
t402/facilitator.py
t402/near_paywall_template.py
t402/networks.py
t402/path.py
t402/paywall.py
t402/py.typed
t402/stacks_paywall_template.py
t402/svm.py
t402/svm_paywall_template.py
t402/ton.py
t402/ton_paywall_template.py
t402/tron.py
t402/tron_paywall_template.py
t402/types.py
t402/bridge/__init__.py
t402/bridge/client.py
t402/bridge/constants.py
t402/bridge/router.py
t402/bridge/scan.py
t402/bridge/types.py
t402/clients/__init__.py
t402/clients/base.py
t402/clients/httpx.py
t402/clients/requests.py
t402/erc4337/__init__.py
t402/erc4337/accounts.py
t402/erc4337/bundlers.py
t402/erc4337/paymasters.py
t402/erc4337/types.py
t402/fastapi/__init__.py
t402/fastapi/dependencies.py
t402/fastapi/middleware.py
t402/flask/__init__.py
t402/flask/middleware.py
t402/mcp/__init__.py
t402/mcp/constants.py
t402/mcp/server.py
t402/mcp/tools.py
t402/mcp/types.py
t402/schemes/__init__.py
t402/schemes/interfaces.py
t402/schemes/registry.py
t402/schemes/aptos/__init__.py
t402/schemes/aptos/constants.py
t402/schemes/aptos/types.py
t402/schemes/aptos/exact_direct/__init__.py
t402/schemes/aptos/exact_direct/client.py
t402/schemes/aptos/exact_direct/facilitator.py
t402/schemes/aptos/exact_direct/server.py
t402/schemes/evm/__init__.py
t402/schemes/evm/exact/__init__.py
t402/schemes/evm/exact/client.py
t402/schemes/evm/exact/facilitator.py
t402/schemes/evm/exact/server.py
t402/schemes/evm/exact_legacy/__init__.py
t402/schemes/evm/exact_legacy/client.py
t402/schemes/evm/exact_legacy/facilitator.py
t402/schemes/evm/exact_legacy/server.py
t402/schemes/evm/upto/__init__.py
t402/schemes/evm/upto/client.py
t402/schemes/evm/upto/facilitator.py
t402/schemes/evm/upto/server.py
t402/schemes/evm/upto/types.py
t402/schemes/near/__init__.py
t402/schemes/near/constants.py
t402/schemes/near/types.py
t402/schemes/near/exact_direct/__init__.py
t402-1.9.1.dist-info/METADATA
t402-1.9.1.dist-info/WHEEL
t402-1.9.1.dist-info/entry_points.txt
t402-1.9.1.dist-info/RECORD
