Metadata-Version: 2.4
Name: t402
Version: 1.9.1
Summary: t402: An internet native payments protocol
Author-email: T402 Team <dev@t402.io>
License: Apache-2.0
Keywords: crypto,payments,sdk,t402,tether,usdt,web3
Requires-Python: >=3.10
Requires-Dist: eth-account>=0.13.7
Requires-Dist: eth-typing>=4.0.0
Requires-Dist: eth-utils>=3.0.0
Requires-Dist: fastapi[standard]>=0.115.12
Requires-Dist: flask>=3.0.0
Requires-Dist: pydantic-settings>=2.2.1
Requires-Dist: pydantic>=2.10.3
Requires-Dist: python-dotenv>=1.0.1
Requires-Dist: web3>=6.0.0
Provides-Extra: all
Requires-Dist: solana>=0.35.0; extra == 'all'
Requires-Dist: solders>=0.21.0; extra == 'all'
Provides-Extra: svm
Requires-Dist: solana>=0.35.0; extra == 'svm'
Requires-Dist: solders>=0.21.0; extra == 'svm'
